reasonable/__init__.py
reasonable/prompts.py
reasonable/agents/__init__.py
reasonable/agents/chain_of_thought.py
reasonable/llms/__init__.py
reasonable/llms/base.py
reasonable/llms/function.py
reasonable_ml-0.3.0.dist-info/METADATA
reasonable_ml-0.3.0.dist-info/WHEEL
reasonable_ml-0.3.0.dist-info/top_level.txt
reasonable_ml-0.3.0.dist-info/RECORD
